{
  "name": "cx-cli (Fedora Bun)",
  "build": {
    "dockerfile": "Dockerfile"
  },
  "workspaceFolder": "/workspace",
  "workspaceMount": "source=${localWorkspaceFolder},target=/workspace,type=bind,consistency=cached",
  "remoteUser": "dev",
  "postCreateCommand": "bun install",
  "customizations": {
    "vscode": {
      "settings": {
        "terminal.integrated.defaultProfile.linux": "fish",
        "terminal.integrated.profiles.linux": {
          "fish": {
            "path": "/usr/bin/fish"
          }
        }
      },
      "extensions": []
    }
  }
}
